wwp/__init__.py
wwp/wwp.py
wwp-1.1.1.dist-info/LICENSE.txt
wwp-1.1.1.dist-info/METADATA
wwp-1.1.1.dist-info/WHEEL
wwp-1.1.1.dist-info/top_level.txt
wwp-1.1.1.dist-info/RECORD
