Metadata-Version: 2.1
Name: wwp
Version: 1.1.1
Summary: Python module for working with prime numbers
Home-page: https://github.com/Langton49/workingWithPrimes
Author: Munashe
Author-email: munashemukweya2022@gmail.com
License: MIT
Keywords: Prime,Numbers,Mathematics,Math
Requires-Python: >=3.10
License-File: LICENSE.txt
Requires-Dist: matplotlib >=3.8.0
Requires-Dist: numpy >=1.26.0
